country_via/__init__.py
country_via/cli.py
country_via/nirsoft.py
country_via/renderer.py
country_via/templates/ip_route.j2
country_via/templates/plain_list.j2
country_via/templates/systemd_network.j2
country_via-0.0.6.dist-info/METADATA
country_via-0.0.6.dist-info/RECORD
country_via-0.0.6.dist-info/WHEEL
country_via-0.0.6.dist-info/entry_points.txt
country_via-0.0.6.dist-info/top_level.txt
