Metadata-Version: 2.1
Name: country-via
Version: 0.0.6
Summary: Route Configuring Tool for Country
Home-page: https://github.com/huiyiqun/country_via
Author: Hui Yiqun
Author-email: huiyiqun@gmail.com
License: MIT
Keywords: network route
Platform: UNKNOWN
Classifier: Development Status :: 3 - Alpha
Classifier: License :: OSI Approved :: MIT License
Classifier: Programming Language :: Python :: 3
Classifier: Programming Language :: Python :: 3.7
Classifier: Intended Audience :: System Administrators
Classifier: Environment :: Console
Requires-Dist: requests
Requires-Dist: jinja2
